{
  "来源": "https://www.amazon.com.mx/gp/bestsellers/pet-supplies/12478521011/",
  "类目": "Artículos para Perros",
  "抓取时间": "2026-07-24T10:18:22.401064",
  "商品总数": 100,
  "商品列表": [
    {
      "排名": 1,
      "ASIN编号": "B07DCJ8B3S",
      "商品名称": "赢家高级犬干粮15kg",
      "品牌": "Ganador",
      "评分": 4.8,
      "评论数": 1688,
      "价格(墨西哥比索)": 659.0,
      "月销量": 6000,
      "销量依据": "亚马逊官方(上月购买量)",
      "上架时间": "2024-05-09",
      "在售月数": 27,
      "变体数量": 1,
      "卖家": "Amazon México",
      "卖家类型": "亚马逊自营",
      "卖家所在地": "",
      "卖家详细地址": "",
      "配送方式": "亚马逊自营配送",
      "商品链接": "https://www.amazon.com.mx/dp/B07DCJ8B3S",
      "完整详情": true
    },
    {
      "排名": 2,
      "ASIN编号": "B08JSG74RV",
      "商品名称": "Ganador优质超级食品20kg中大型犬成犬粮",
      "品牌": "Ganador",
      "评分": 4.6,
      "评论数": 2900,
      "价格(墨西哥比索)": 899.0,
      "月销量": 5000,
      "销量依据": "亚马逊官方(上月购买量)",
      "上架时间": "2020-09-22",
      "在售月数": 70,
      "变体数量": 1,
      "卖家": "Amazon México",
      "卖家类型": "亚马逊自营",
      "卖家所在地": "",
      "卖家详细地址": "",
      "配送方式": "亚马逊自营配送",
      "商品链接": "https://www.amazon.com.mx/dp/B08JSG74RV",
      "完整详情": true
    },
    {
      "排名": 3,
      "ASIN编号": "B0B45W18MJ",
      "商品名称": "MESVIER 中小大型犬胸背带 带1.5米牵引绳，可调节反光透气，防爆冲狗背带 用于散步旅行训练 宠物配件",
      "品牌": "MESVIER",
      "评分": 4.7,
      "评论数": 9581,
      "价格(墨西哥比索)": 249.0,
      "月销量": 200,
      "销量依据": "亚马逊官方(上月购买量)",
      "上架时间": "2022-07-21",
      "在售月数": 48,
      "变体数量": 43,
      "卖家": "MESVIER",
      "卖家类型": "品牌方(中国)",
      "卖家所在地": "中国",
      "卖家详细地址": "中国/518104/广东/宝安区/深圳/民主社区蚝三民主丰泽园5、6、7、8、9栋7栋1402/沙井街道",
      "配送方式": "FBA",
      "商品链接": "https://www.amazon.com.mx/dp/B0B45W18MJ",
      "完整详情": true
    },
    {
      "排名": 4,
      "ASIN编号": "B00NABTG60",
      "商品名称": "Amazon Basics - 狗便袋，带分配器，黑色，600只（40卷），升级防漏，无香，含牵引夹",
      "品牌": "Amazon Basics",
      "评分": 4.9,
      "评论数": 235390,
      "价格(墨西哥比索)": 262.87,
      "月销量": 1000,
      "销量依据": "亚马逊官方(上月购买量)",
      "上架时间": "2017-09-11",
      "在售月数": 107,
      "变体数量": 6,
      "卖家": "Amazon México",
      "卖家类型": "亚马逊自营",
      "卖家所在地": "",
      "卖家详细地址": "",
      "配送方式": "亚马逊自营配送",
      "商品链接": "https://www.amazon.com.mx/dp/B00NABTG60",
      "完整详情": true
    },
    {
      "排名": 5,
      "ASIN编号": "B0153V4AOM",
      "商品名称": "Nupec 狗粮，小型犬成年犬粮，含Omega 3和6，8公斤装",
      "品牌": "Nupec",
      "评分": 4.8,
      "评论数": 15727,
      "价格(墨西哥比索)": 1160.31,
      "月销量": 7000,
      "销量依据": "亚马逊官方(上月购买量)",
      "上架时间": "2015-09-01",
      "在售月数": 131,
      "变体数量": 1,
      "卖家": "Amazon México",
      "卖家类型": "亚马逊自营",
      "卖家所在地": "",
      "卖家详细地址": "",
      "配送方式": "亚马逊自营配送",
      "商品链接": "https://www.amazon.com.mx/dp/B0153V4AOM",
      "完整详情": true
    },
    {
      "排名": 6,
      "ASIN编号": "B01MQFPHMN",
      "商品名称": "Ganador Premium 成年犬粮 20公斤，小型犬种，黑色。包装可能不同。",
      "品牌": "Ganador",
      "评分": 4.7,
      "评论数": 2585,
      "价格(墨西哥比索)": 888.0,
      "月销量": 4000,
      "销量依据": "亚马逊官方(上月购买量)",
      "上架时间": "2016-11-08",
      "在售月数": 117,
      "变体数量": 1,
      "卖家": "Amazon México",
      "卖家类型": "亚马逊自营",
      "卖家所在地": "",
      "卖家详细地址": "",
      "配送方式": "亚马逊自营配送",
      "商品链接": "https://www.amazon.com.mx/dp/B01MQFPHMN",
      "完整详情": true
    },
    {
      "排名": 7,
      "ASIN编号": "B01N0AG6OF",
      "商品名称": "Ganador Premium幼犬粮20kg，适用于中大型犬。包装可能不同。",
      "品牌": "Ganador",
      "评分": 4.7,
      "评论数": 4792,
      "价格(墨西哥比索)": 868.0,
      "月销量": 4000,
      "销量依据": "亚马逊官方(上月购买量)",
      "上架时间": "2016-11-08",
      "在售月数": 117,
      "变体数量": 1,
      "卖家": "Amazon México",
      "卖家类型": "亚马逊自营",
      "卖家所在地": "",
      "卖家详细地址": "",
      "配送方式": "亚马逊自营配送",
      "商品链接": "https://www.amazon.com.mx/dp/B01N0AG6OF",
      "完整详情": true
    },
    {
      "排名": 8,
      "ASIN编号": "B0CXYTC8WM",
      "商品名称": "佳纳多干狗粮20kg",
      "品牌": "Ganador",
      "评分": 4.7,
      "评论数": 1701,
      "价格(墨西哥比索)": 705.0,
      "月销量": 5000,
      "销量依据": "亚马逊官方(上月购买量)",
      "上架时间": "2024-03-13",
      "在售月数": 28,
      "变体数量": 1,
      "卖家": "Amazon México",
      "卖家类型": "亚马逊自营",
      "卖家所在地": "",
      "卖家详细地址": "",
      "配送方式": "亚马逊自营配送",
      "商品链接": "https://www.amazon.com.mx/dp/B0CXYTC8WM",
      "完整详情": true
    },
    {
      "排名": 9,
      "ASIN编号": "B0153V49XO",
      "商品名称": "Nupec 成年小型犬狗粮，含Omega 3和6，2kg装",
      "品牌": "Nupec",
      "评分": 4.8,
      "评论数": 8515,
      "价格(墨西哥比索)": 362.94,
      "月销量": 4000,
      "销量依据": "亚马逊官方(上月购买量)",
      "上架时间": "2015-09-01",
      "在售月数": 131,
      "变体数量": 1,
      "卖家": "Amazon México",
      "卖家类型": "亚马逊自营",
      "卖家所在地": "",
      "卖家详细地址": "",
      "配送方式": "亚马逊自营配送",
      "商品链接": "https://www.amazon.com.mx/dp/B0153V49XO",
      "完整详情": true
    },
    {
      "排名": 10,
      "ASIN编号": "B0D43R8KKL",
      "商品名称": "Fancy Pets MS 鲑鱼油 250ml 狗猫通用 - Omega-3 含 DHA 和 EPA - 健康皮肤、亮丽毛发、强健免疫系统",
      "品牌": "Medical Solutions",
      "评分": 4.5,
      "评论数": 2034,
      "价格(墨西哥比索)": 149.0,
      "月销量": 1000,
      "销量依据": "亚马逊官方(上月购买量)",
      "上架时间": "2024-05-13",
      "在售月数": 26,
      "变体数量": 3,
      "卖家": "Amazon México",
      "卖家类型": "亚马逊自营",
      "卖家所在地": "",
      "卖家详细地址": "",
      "配送方式": "亚马逊自营配送",
      "商品链接": "https://www.amazon.com.mx/dp/B0D43R8KKL",
      "完整详情": true
    },
    {
      "排名": 11,
      "ASIN编号": "B01N30FXOM",
      "商品名称": "冠能成年迷你和小型犬粮 牛肉鸡肉味 7.5公斤",
      "品牌": "Dog Chow",
      "评分": 4.8,
      "评论数": 4916,
      "价格(墨西哥比索)": 336.0,
      "月销量": 3000,
      "销量依据": "亚马逊官方(上月购买量)",
      "上架时间": "2017-01-24",
      "在售月数": 114,
      "变体数量": 1,
      "卖家": "Amazon México",
      "卖家类型": "亚马逊自营",
      "卖家所在地": "",
      "卖家详细地址": "",
      "配送方式": "亚马逊自营配送",
      "商品链接": "https://www.amazon.com.mx/dp/B01N30FXOM",
      "完整详情": true
    },
    {
      "排名": 12,
      "ASIN编号": "B09R93SSD5",
      "商品名称": "Purina Beneful成犬全犬种三文鱼味10公斤",
      "品牌": "Purina",
      "评分": 4.8,
      "评论数": 4303,
      "价格(墨西哥比索)": 553.0,
      "月销量": 3000,
      "销量依据": "亚马逊官方(上月购买量)",
      "上架时间": "2022-01-26",
      "在售月数": 54,
      "变体数量": 1,
      "卖家": "Amazon México",
      "卖家类型": "亚马逊自营",
      "卖家所在地": "",
      "卖家详细地址": "",
      "配送方式": "亚马逊自营配送",
      "商品链接": "https://www.amazon.com.mx/dp/B09R93SSD5",
      "完整详情": true
    },
    {
      "排名": 13,
      "ASIN编号": "B018M8AR90",
      "商品名称": "Dry Pet 狗狗训练垫30片装",
      "品牌": "Dry Pet",
      "评分": 4.6,
      "评论数": 3744,
      "价格(墨西哥比索)": 159.81,
      "月销量": 2000,
      "销量依据": "亚马逊官方(上月购买量)",
      "上架时间": "2016-05-06",
      "在售月数": 123,
      "变体数量": 5,
      "卖家": "Amazon México",
      "卖家类型": "亚马逊自营",
      "卖家所在地": "",
      "卖家详细地址": "",
      "配送方式": "亚马逊自营配送",
      "商品链接": "https://www.amazon.com.mx/dp/B018M8AR90",
      "完整详情": true
    },
    {
      "排名": 14,
      "ASIN编号": "B0153V41AU",
      "商品名称": "Nupec成年犬粮含Omega 3和6 - 1包x15公斤",
      "品牌": "Nupec",
      "评分": 4.8,
      "评论数": 7967,
      "价格(墨西哥比索)": 1735.97,
      "月销量": 4000,
      "销量依据": "亚马逊官方(上月购买量)",
      "上架时间": "2015-09-01",
      "在售月数": 131,
      "变体数量": 1,
      "卖家": "Amazon México",
      "卖家类型": "亚马逊自营",
      "卖家所在地": "",
      "卖家详细地址": "",
      "配送方式": "亚马逊自营配送",
      "商品链接": "https://www.amazon.com.mx/dp/B0153V41AU",
      "完整详情": true
    },
    {
      "排名": 15,
      "ASIN编号": "B0153V7ZTO",
      "商品名称": "Purina Dog Chow成年中型大型犬牛肉鸡肉味7.5kg",
      "品牌": "Dog Chow",
      "评分": 4.8,
      "评论数": 4115,
      "价格(墨西哥比索)": 336.0,
      "月销量": 2000,
      "销量依据": "亚马逊官方(上月购买量)",
      "上架时间": "2016-11-24",
      "在售月数": 116,
      "变体数量": 1,
      "卖家": "Amazon México",
      "卖家类型": "亚马逊自营",
      "卖家所在地": "",
      "卖家详细地址": "",
      "配送方式": "亚马逊自营配送",
      "商品链接": "https://www.amazon.com.mx/dp/B0153V7ZTO",
      "完整详情": true
    },
    {
      "排名": 16,
      "ASIN编号": "B0CF4BLG83",
      "商品名称": "Dogelthy Mobility 狗狗关节保护粉，含葡萄糖胺、软骨素和UCII型胶原蛋白，用于狗粮或生骨肉饮食，270克（鱼肉味）",
      "品牌": "Dogelthy",
      "评分": 4.6,
      "评论数": 2098,
      "价格(墨西哥比索)": 824.25,
      "月销量": 1000,
      "销量依据": "亚马逊官方(上月购买量)",
      "上架时间": "2023-08-09",
      "在售月数": 36,
      "变体数量": 4,
      "卖家": "Dogelthy",
      "卖家类型": "品牌方(墨西哥)",
      "卖家所在地": "墨西哥",
      "卖家详细地址": "墨西哥/45019/哈利斯科/萨波潘/圣胡安·德奥科坦/5月5日 #15 内部6",
      "配送方式": "FBA",
      "商品链接": "https://www.amazon.com.mx/dp/B0CF4BLG83",
      "完整详情": true
    },
    {
      "排名": 17,
      "ASIN编号": "B0CF63JSS9",
      "商品名称": "Dogelthy 纯三文鱼油 450毫升，每份含300毫克EPA+DHA的狗狗Omega-3鱼油补充剂，适用于狗粮或生骨肉饮食",
      "品牌": "Dogelthy",
      "评分": 4.7,
      "评论数": 3032,
      "价格(墨西哥比索)": 509.0,
      "月销量": 1000,
      "销量依据": "亚马逊官方(上月购买量)",
      "上架时间": "2023-08-09",
      "在售月数": 36,
      "变体数量": 3,
      "卖家": "Dogelthy",
      "卖家类型": "品牌方(墨西哥)",
      "卖家所在地": "墨西哥",
      "卖家详细地址": "墨西哥/45019/哈利斯科州/萨波潘/圣胡安-德奥科坦/五月五日 #15内6",
      "配送方式": "FBA",
      "商品链接": "https://www.amazon.com.mx/dp/B0CF63JSS9",
      "完整详情": true
    },
    {
      "排名": 18,
      "ASIN编号": "B003CL6Q84",
      "商品名称": "希尔思科学饮食小型及迷你成犬粮（鸡肉味）7kg，有助于构建长期健康基础，呵护皮肤和毛发",
      "品牌": "Hill's Science Diet",
      "评分": 4.8,
      "评论数": 25360,
      "价格(墨西哥比索)": 960.0,
      "月销量": 1000,
      "销量依据": "亚马逊官方(上月购买量)",
      "上架时间": "2013-07-08",
      "在售月数": 157,
      "变体数量": 2,
      "卖家": "Amazon México",
      "卖家类型": "亚马逊自营",
      "卖家所在地": "",
      "卖家详细地址": "",
      "配送方式": "亚马逊自营配送",
      "商品链接": "https://www.amazon.com.mx/dp/B003CL6Q84",
      "完整详情": true
    },
    {
      "排名": 19,
      "ASIN编号": "B01FKNX3FU",
      "商品名称": "Ganador 成犬小型犬粮 20公斤 蓝色",
      "品牌": "Ganador",
      "评分": 4.8,
      "评论数": 1530,
      "价格(墨西哥比索)": 678.0,
      "月销量": 2000,
      "销量依据": "亚马逊官方(上月购买量)",
      "上架时间": "2016-11-24",
      "在售月数": 116,
      "变体数量": 1,
      "卖家": "Amazon México",
      "卖家类型": "亚马逊自营",
      "卖家所在地": "",
      "卖家详细地址": "",
      "配送方式": "亚马逊自营配送",
      "商品链接": "https://www.amazon.com.mx/dp/B01FKNX3FU",
      "完整详情": true
    },
    {
      "排名": 20,
      "ASIN编号": "B07XZHXZW4",
      "商品名称": "HI MULTI PRO 优质成犬粮 25kg，含益生菌和高生物价值蛋白质",
      "品牌": "HI MULTI PRO",
      "评分": 4.6,
      "评论数": 6547,
      "价格(墨西哥比索)": 1154.0,
      "月销量": 1000,
      "销量依据": "亚马逊官方(上月购买量)",
      "上架时间": "2015-10-07",
      "在售月数": 130,
      "变体数量": 3,
      "卖家": "ALBAPESA",
      "卖家类型": "第三方(墨西哥)",
      "卖家所在地": "墨西哥",
      "卖家详细地址": "墨西哥/36900/瓜纳华托/彭哈莫/63公里 伊拉普阿托-拉彼达公路",
      "配送方式": "FBA",
      "商品链接": "https://www.amazon.com.mx/dp/B07XZHXZW4",
      "完整详情": true
    },
    {
      "排名": 21,
      "ASIN编号": "B0B1W1ZZGQ",
      "商品名称": "伊纳巴猫咪奶油零食 4种金枪鱼口味 低卡 50支*14g",
      "品牌": "INABA",
      "评分": 4.9,
      "评论数": 1530,
      "价格(墨西哥比索)": 675.0,
      "月销量": 2000,
      "销量依据": "亚马逊官方(上月购买量)",
      "上架时间": "2023-10-29",
      "在售月数": 33,
      "变体数量": 18,
      "卖家": "Amazon México",
      "卖家类型": "亚马逊自营",
      "卖家所在地": "",
      "卖家详细地址": "",
      "配送方式": "亚马逊自营配送",
      "商品链接": "https://www.amazon.com.mx/dp/B0B1W1ZZGQ",
      "完整详情": true
    },
    {
      "排名": 22,
      "ASIN编号": "B09R916GQ3",
      "商品名称": "普瑞纳 Beneful 成犬原味牛肉粮 10公斤",
      "品牌": "WeTap",
      "评分": 4.8,
      "评论数": 2650,
      "价格(墨西哥比索)": 474.0,
      "月销量": 2000,
      "销量依据": "亚马逊官方(上月购买量)",
      "上架时间": "2022-01-26",
      "在售月数": 54,
      "变体数量": 1,
      "卖家": "Amazon México",
      "卖家类型": "亚马逊自营",
      "卖家所在地": "",
      "卖家详细地址": "",
      "配送方式": "亚马逊自营配送",
      "商品链接": "https://www.amazon.com.mx/dp/B09R916GQ3",
      "完整详情": true
    },
    {
      "排名": 23,
      "ASIN编号": "B0118VV13O",
      "商品名称": "Hill's 天然训练软嚼零食，犬用训练奖励，90克",
      "品牌": "Hill's",
      "评分": 4.7,
      "评论数": 3895,
      "价格(墨西哥比索)": 82.5,
      "月销量": 500,
      "销量依据": "亚马逊官方(上月购买量)",
      "上架时间": "2016-06-24",
      "在售月数": 121,
      "变体数量": 5,
      "卖家": "Amazon México",
      "卖家类型": "亚马逊自营",
      "卖家所在地": "",
      "卖家详细地址": "",
      "配送方式": "亚马逊自营配送",
      "商品链接": "https://www.amazon.com.mx/dp/B0118VV13O",
      "完整详情": true
    },
    {
      "排名": 24,
      "ASIN编号": "B07TGKCWWP",
      "商品名称": "Dry Pet 狗狗纸尿裤小号12片装",
      "品牌": "Fancy Pets",
      "评分": 4.5,
      "评论数": 1451,
      "价格(墨西哥比索)": 131.53,
      "月销量": 600,
      "销量依据": "亚马逊官方(上月购买量)",
      "上架时间": "2019-06-25",
      "在售月数": 85,
      "变体数量": 4,
      "卖家": "Amazon México",
      "卖家类型": "亚马逊自营",
      "卖家所在地": "",
      "卖家详细地址": "",
      "配送方式": "亚马逊自营配送",
      "商品链接": "https://www.amazon.com.mx/dp/B07TGKCWWP",
      "完整详情": true
    },
    {
      "排名": 25,
      "ASIN编号": "B0153V43UI",
      "商品名称": "Nupec 狗粮，成犬，含Omega 3和6，5公斤装",
      "品牌": "Nupec",
      "评分": 4.8,
      "评论数": 4017,
      "价格(墨西哥比索)": 753.0,
      "月销量": 600,
      "销量依据": "亚马逊官方(上月购买量)",
      "上架时间": "2015-09-01",
      "在售月数": 131,
      "变体数量": 3,
      "卖家": "AniMALL",
      "卖家类型": "第三方(墨西哥)",
      "卖家所在地": "墨西哥",
      "卖家详细地址": "墨西哥/03500/贝尼托·华雷斯/墨西哥城/纳蒂维塔斯/路易莎 136",
      "配送方式": "FBA",
      "商品链接": "https://www.amazon.com.mx/dp/B0153V43UI",
      "完整详情": true
    },
    {
      "排名": 26,
      "ASIN编号": "B071HPBSHV",
      "商品名称": "Amazon Basics 公狗尿布，30片装，小号，超吸水一次性包裹式，安全贴合，防漏舒适",
      "品牌": "Amazon Basics",
      "评分": 4.5,
      "评论数": 32205,
      "价格(墨西哥比索)": 364.9,
      "月销量": 600,
      "销量依据": "亚马逊官方(上月购买量)",
      "上架时间": "2017-10-23",
      "在售月数": 105,
      "变体数量": 4,
      "卖家": "Amazon México",
      "卖家类型": "亚马逊自营",
      "卖家所在地": "",
      "卖家详细地址": "",
      "配送方式": "亚马逊自营配送",
      "商品链接": "https://www.amazon.com.mx/dp/B071HPBSHV",
      "完整详情": true
    },
    {
      "排名": 27,
      "ASIN编号": "B0BBSG79MX",
      "商品名称": "Pedigree 高蛋白成年犬粮，牛肉和鸡肉口味，24袋，每袋85克，含蛋白质、抗氧化剂和维生素E",
      "品牌": "Pedigree",
      "评分": 4.8,
      "评论数": 1149,
      "价格(墨西哥比索)": 252.2,
      "月销量": null,
      "销量依据": "",
      "上架时间": "2022-08-24",
      "在售月数": 47,
      "变体数量": 1,
      "卖家": "",
      "卖家类型": "",
      "卖家所在地": "",
      "卖家详细地址": "",
      "配送方式": "",
      "商品链接": "https://www.amazon.com.mx/dp/B0BBSG79MX",
      "完整详情": true
    },
    {
      "排名": 28,
      "ASIN编号": "B0153V4056",
      "商品名称": "Nupec狗粮，成犬幼犬通用，含维生素E和硒，8公斤装",
      "品牌": "Nupec",
      "评分": 4.8,
      "评论数": 9503,
      "价格(墨西哥比索)": 1094.0,
      "月销量": 300,
      "销量依据": "亚马逊官方(上月购买量)",
      "上架时间": "2015-09-01",
      "在售月数": 131,
      "变体数量": 5,
      "卖家": "Amazon México",
      "卖家类型": "亚马逊自营",
      "卖家所在地": "",
      "卖家详细地址": "",
      "配送方式": "亚马逊自营配送",
      "商品链接": "https://www.amazon.com.mx/dp/B0153V4056",
      "完整详情": true
    },
    {
      "排名": 29,
      "ASIN编号": "B09WXGR63N",
      "商品名称": "战术狗项圈，军用加厚尼龙带手柄，可调节金属扣训练项圈，舒适（卡其色，大号）",
      "品牌": "DAQI",
      "评分": 4.7,
      "评论数": 935,
      "价格(墨西哥比索)": 165.44,
      "月销量": 200,
      "销量依据": "亚马逊官方(上月购买量)",
      "上架时间": "2022-04-03",
      "在售月数": 52,
      "变体数量": 15,
      "卖家": "CHIYING",
      "卖家类型": "第三方(中国)",
      "卖家所在地": "中国",
      "卖家详细地址": "中国/06000/广东省/龙岗区/深圳市/坂田街道万科城社区新天下百瑞达大厦四层401室",
      "配送方式": "FBA",
      "商品链接": "https://www.amazon.com.mx/dp/B09WXGR63N",
      "完整详情": true
    },
    {
      "排名": 30,
      "ASIN编号": "B0B43X13C2",
      "商品名称": "狗床，耐用，舒适，柔软填充，尺寸和颜色可选（中号，黑色/灰色）",
      "品牌": "PETS APPAREL HILLS",
      "评分": 4.6,
      "评论数": 10392,
      "价格(墨西哥比索)": 399.2,
      "月销量": 100,
      "销量依据": "亚马逊官方(上月购买量)",
      "上架时间": "2022-06-14",
      "在售月数": 49,
      "变体数量": 50,
      "卖家": "I Jacket",
      "卖家类型": "第三方(墨西哥)",
      "卖家所在地": "墨西哥",
      "卖家详细地址": "墨西哥/06090/墨西哥城/库奥特莫克/内萨瓦尔科约特尔/158公寓202",
      "配送方式": "FBA",
      "商品链接": "https://www.amazon.com.mx/dp/B0B43X13C2",
      "完整详情": true
    },
    {
      "排名": 31,
      "ASIN编号": "B01FVRF920",
      "商品名称": "Barkys 80136100614 肉干棒 1千克，1件，小号",
      "品牌": "BARKYS",
      "评分": 4.8,
      "评论数": 1562,
      "价格(墨西哥比索)": 199.0,
      "月销量": 2000,
      "销量依据": "亚马逊官方(上月购买量)",
      "上架时间": "2016-05-19",
      "在售月数": 122,
      "变体数量": 1,
      "卖家": "Amazon México",
      "卖家类型": "亚马逊自营",
      "卖家所在地": "",
      "卖家详细地址": "",
      "配送方式": "亚马逊自营配送",
      "商品链接": "https://www.amazon.com.mx/dp/B01FVRF920",
      "完整详情": true
    },
    {
      "排名": 32,
      "ASIN编号": "B07PY5FGR1",
      "商品名称": "Cloralex宠物除臭剂 3.75升",
      "品牌": "Cloralex",
      "评分": 4.8,
      "评论数": 2477,
      "价格(墨西哥比索)": 85.0,
      "月销量": 1000,
      "销量依据": "亚马逊官方(上月购买量)",
      "上架时间": "",
      "在售月数": null,
      "变体数量": 1,
      "卖家": "Amazon México",
      "卖家类型": "亚马逊自营",
      "卖家所在地": "",
      "卖家详细地址": "",
      "配送方式": "亚马逊自营配送",
      "商品链接": "https://www.amazon.com.mx/dp/B07PY5FGR1",
      "完整详情": true
    },
    {
      "排名": 33,
      "ASIN编号": "B016C6EJ4S",
      "商品名称": "Amazon Basics 宠物训练尿垫，5层防漏速干，超大号71×86cm，40片装，蓝白双色",
      "品牌": "Amazon Basics",
      "评分": 4.5,
      "评论数": 216939,
      "价格(墨西哥比索)": 492.92,
      "月销量": 400,
      "销量依据": "亚马逊官方(上月购买量)",
      "上架时间": "2025-01-11",
      "在售月数": 18,
      "变体数量": 6,
      "卖家": "Amazon México",
      "卖家类型": "亚马逊自营",
      "卖家所在地": "",
      "卖家详细地址": "",
      "配送方式": "亚马逊自营配送",
      "商品链接": "https://www.amazon.com.mx/dp/B016C6EJ4S",
      "完整详情": true
    },
    {
      "排名": 34,
      "ASIN编号": "B01FUDI7F6",
      "商品名称": "Nupec老年犬狗粮，15公斤装",
      "品牌": "Nupec",
      "评分": 4.8,
      "评论数": 5199,
      "价格(墨西哥比索)": 2180.0,
      "月销量": 1000,
      "销量依据": "亚马逊官方(上月购买量)",
      "上架时间": "2016-05-18",
      "在售月数": 122,
      "变体数量": 3,
      "卖家": "COMERCIALIZADORA RIPO",
      "卖家类型": "第三方(墨西哥)",
      "卖家所在地": "墨西哥",
      "卖家详细地址": "墨西哥/72830/普埃布拉/圣安德烈斯乔卢拉/帕塞奥德塔拉曼特斯 156",
      "配送方式": "FBA",
      "商品链接": "https://www.amazon.com.mx/dp/B01FUDI7F6",
      "完整详情": true
    },
    {
      "排名": 35,
      "ASIN编号": "B0971C67PW",
      "商品名称": "Purina Fancy Feast 成猫牛肉小肉片 85g 12包",
      "品牌": "WeTap",
      "评分": 4.7,
      "评论数": 415,
      "价格(墨西哥比索)": 204.0,
      "月销量": 1000,
      "销量依据": "亚马逊官方(上月购买量)",
      "上架时间": "2021-06-10",
      "在售月数": 62,
      "变体数量": 1,
      "卖家": "Amazon México",
      "卖家类型": "亚马逊自营",
      "卖家所在地": "",
      "卖家详细地址": "",
      "配送方式": "亚马逊自营配送",
      "商品链接": "https://www.amazon.com.mx/dp/B0971C67PW",
      "完整详情": true
    },
    {
      "排名": 36,
      "ASIN编号": "B0DF4TZZ82",
      "商品名称": "Dogelthy 100%天然脱水鸡爪，无防腐剂和人造香精的狗狗零食，幼犬、成犬、老年犬均适用，每袋10只。",
      "品牌": "Dogelthy",
      "评分": 4.4,
      "评论数": 75,
      "价格(墨西哥比索)": 210.0,
      "月销量": 400,
      "销量依据": "亚马逊官方(上月购买量)",
      "上架时间": "2024-08-23",
      "在售月数": 23,
      "变体数量": 5,
      "卖家": "Dogelthy",
      "卖家类型": "品牌方(墨西哥)",
      "卖家所在地": "墨西哥",
      "卖家详细地址": "墨西哥/45019/哈利斯科/萨波潘/圣胡安-德奥科坦/5月5日 #15 内6",
      "配送方式": "FBA",
      "商品链接": "https://www.amazon.com.mx/dp/B0DF4TZZ82",
      "完整详情": true
    },
    {
      "排名": 37,
      "ASIN编号": "B075N8M4BQ",
      "商品名称": "Cesar 菲力牛排原汁狗粮 24袋 每袋75克",
      "品牌": "Cesar",
      "评分": 4.7,
      "评论数": 795,
      "价格(墨西哥比索)": 220.0,
      "月销量": 500,
      "销量依据": "亚马逊官方(上月购买量)",
      "上架时间": "2017-09-11",
      "在售月数": 107,
      "变体数量": 4,
      "卖家": "Amazon México",
      "卖家类型": "亚马逊自营",
      "卖家所在地": "",
      "卖家详细地址": "",
      "配送方式": "亚马逊自营配送",
      "商品链接": "https://www.amazon.com.mx/dp/B075N8M4BQ",
      "完整详情": true
    },
    {
      "排名": 38,
      "ASIN编号": "B0CK32S653",
      "商品名称": "Waggys三文鱼小食，无谷物天然狗零食，100粒装",
      "品牌": "Waggys",
      "评分": 4.6,
      "评论数": 639,
      "价格(墨西哥比索)": 189.0,
      "月销量": 1000,
      "销量依据": "亚马逊官方(上月购买量)",
      "上架时间": "2023-09-28",
      "在售月数": 34,
      "变体数量": 2,
      "卖家": "Waggy´s!",
      "卖家类型": "品牌方(墨西哥)",
      "卖家所在地": "墨西哥",
      "卖家详细地址": "墨西哥/44520/哈利斯科/瓜达拉哈拉/拉萨罗·卡德纳斯 3454",
      "配送方式": "FBA",
      "商品链接": "https://www.amazon.com.mx/dp/B0CK32S653",
      "完整详情": true
    },
    {
      "排名": 39,
      "ASIN编号": "B08NWZD6MS",
      "商品名称": "Spring Blossoms 专业二合一猫狗美容梳，轻松去除毛结缠结，安全宠物刷（橙色）",
      "品牌": "Spring Blossoms",
      "评分": 4.7,
      "评论数": 4268,
      "价格(墨西哥比索)": 297.99,
      "月销量": 800,
      "销量依据": "亚马逊官方(上月购买量)",
      "上架时间": "2021-01-06",
      "在售月数": 67,
      "变体数量": 4,
      "卖家": "GoodHappens",
      "卖家类型": "第三方(中国)",
      "卖家所在地": "中国",
      "卖家详细地址": "中国/361000/福建/厦门市/205-11室之三/火炬高新区软件园二期观日路8号",
      "配送方式": "FBA",
      "商品链接": "https://www.amazon.com.mx/dp/B08NWZD6MS",
      "完整详情": true
    },
    {
      "排名": 40,
      "ASIN编号": "B0CDYWTMRM",
      "商品名称": "Purina Dog Chow 成年犬全犬种 牛肉鸡肉味 18公斤",
      "品牌": "Dog Chow",
      "评分": 4.7,
      "评论数": 549,
      "价格(墨西哥比索)": 720.0,
      "月销量": 500,
      "销量依据": "亚马逊官方(上月购买量)",
      "上架时间": "2023-08-07",
      "在售月数": 36,
      "变体数量": 1,
      "卖家": "Amazon México",
      "卖家类型": "亚马逊自营",
      "卖家所在地": "",
      "卖家详细地址": "",
      "配送方式": "亚马逊自营配送",
      "商品链接": "https://www.amazon.com.mx/dp/B0CDYWTMRM",
      "完整详情": true
    },
    {
      "排名": 41,
      "ASIN编号": "B0723HRWJW",
      "商品名称": "Nature's Miracle - 狗狗污渍异味去除剂 - 946毫升 - 先进配方 - 清除顽固污渍 - 中和异味 - 适用于家具、地毯、硬质地板和织物",
      "品牌": "Nature's Miracle",
      "评分": 4.4,
      "评论数": 23280,
      "价格(墨西哥比索)": 224.25,
      "月销量": 1000,
      "销量依据": "亚马逊官方(上月购买量)",
      "上架时间": "2017-06-29",
      "在售月数": 109,
      "变体数量": 3,
      "卖家": "Amazon México",
      "卖家类型": "亚马逊自营",
      "卖家所在地": "",
      "卖家详细地址": "",
      "配送方式": "亚马逊自营配送",
      "商品链接": "https://www.amazon.com.mx/dp/B0723HRWJW",
      "完整详情": true
    },
    {
      "排名": 42,
      "ASIN编号": "B01FUDI7OC",
      "商品名称": "Nupec狗粮，体重控制，适用于超重或肥胖犬只的营养配方，15公斤装。",
      "品牌": "Nupec",
      "评分": 4.8,
      "评论数": 3938,
      "价格(墨西哥比索)": 2189.0,
      "月销量": 1000,
      "销量依据": "亚马逊官方(上月购买量)",
      "上架时间": "2016-05-18",
      "在售月数": 122,
      "变体数量": 3,
      "卖家": "Selectashop",
      "卖家类型": "第三方(墨西哥)",
      "卖家所在地": "墨西哥",
      "卖家详细地址": "墨西哥/01729/墨西哥城/墨西哥城/阿尔坎塔里利亚/德西埃托德洛斯莱昂内斯 5547 INT B605",
      "配送方式": "",
      "商品链接": "https://www.amazon.com.mx/dp/B01FUDI7OC",
      "完整详情": true
    },
    {
      "排名": 43,
      "ASIN编号": "B0855ND74T",
      "商品名称": "PetLovers 600片衣物除毛絮纸套装 - 超粘除毛絮滚筒, 宠物除毛滚筒 - 6件装",
      "品牌": "PetLovers",
      "评分": 4.8,
      "评论数": 357,
      "价格(墨西哥比索)": 364.04,
      "月销量": 300,
      "销量依据": "亚马逊官方(上月购买量)",
      "上架时间": "",
      "在售月数": null,
      "变体数量": 4,
      "卖家": "PetLovers MX",
      "卖家类型": "品牌方(美国)",
      "卖家所在地": "美国",
      "卖家详细地址": "美国/33702/佛罗里达州/圣彼得斯堡/7901 第4街北 套房300",
      "配送方式": "FBA",
      "商品链接": "https://www.amazon.com.mx/dp/B0855ND74T",
      "完整详情": true
    },
    {
      "排名": 44,
      "ASIN编号": "B09Z6QHGTG",
      "商品名称": "带LED灯的猫狗指甲剪：照亮指甲或血线，确保安全修剪。超锋利刀片适用于厚指甲，快速感应器防止过度修剪。适合猫狗使用。",
      "品牌": "Elvess",
      "评分": 4.7,
      "评论数": 1698,
      "价格(墨西哥比索)": 195.65,
      "月销量": 1000,
      "销量依据": "亚马逊官方(上月购买量)",
      "上架时间": "2022-04-29",
      "在售月数": 51,
      "变体数量": 1,
      "卖家": "elvess",
      "卖家类型": "品牌方(墨西哥)",
      "卖家所在地": "墨西哥",
      "卖家详细地址": "墨西哥/518000/广东/深圳/龙岗区龙城街道爱联社区金华街73号301",
      "配送方式": "FBA",
      "商品链接": "https://www.amazon.com.mx/dp/B09Z6QHGTG",
      "完整详情": true
    },
    {
      "排名": 45,
      "ASIN编号": "B0BQTFBXHP",
      "商品名称": "希尔思科学饮食小颗粒老年犬粮7+，鸡肉糙米口味，6.8公斤",
      "品牌": "Hill's Science Diet",
      "评分": 4.7,
      "评论数": 478,
      "价格(墨西哥比索)": 1152.0,
      "月销量": 1000,
      "销量依据": "亚马逊官方(上月购买量)",
      "上架时间": "2022-12-22",
      "在售月数": 43,
      "变体数量": 1,
      "卖家": "Amazon México",
      "卖家类型": "亚马逊自营",
      "卖家所在地": "",
      "卖家详细地址": "",
      "配送方式": "亚马逊自营配送",
      "商品链接": "https://www.amazon.com.mx/dp/B0BQTFBXHP",
      "完整详情": true
    },
    {
      "排名": 46,
      "ASIN编号": "B09Y1R1GWL",
      "商品名称": "宝路小体型犬牛肉片味湿粮包，含天然成分、蛋白质和纤维，24包，每包100克",
      "品牌": "Pedigree",
      "评分": 4.8,
      "评论数": 901,
      "价格(墨西哥比索)": 225.25,
      "月销量": 600,
      "销量依据": "亚马逊官方(上月购买量)",
      "上架时间": "2022-04-15",
      "在售月数": 51,
      "变体数量": 1,
      "卖家": "Amazon México",
      "卖家类型": "亚马逊自营",
      "卖家所在地": "",
      "卖家详细地址": "",
      "配送方式": "亚马逊自营配送",
      "商品链接": "https://www.amazon.com.mx/dp/B09Y1R1GWL",
      "完整详情": true
    },
    {
      "排名": 47,
      "ASIN编号": "B01M8G9HYE",
      "商品名称": "Nupec PENU7138 - AAAAAA 狗狗放松零食，180克（包装可能不同）",
      "品牌": "Nupec",
      "评分": 4.6,
      "评论数": 5433,
      "价格(墨西哥比索)": 113.0,
      "月销量": 1000,
      "销量依据": "亚马逊官方(上月购买量)",
      "上架时间": "2016-11-02",
      "在售月数": 117,
      "变体数量": 1,
      "卖家": "Amazon México",
      "卖家类型": "亚马逊自营",
      "卖家所在地": "",
      "卖家详细地址": "",
      "配送方式": "亚马逊自营配送",
      "商品链接": "https://www.amazon.com.mx/dp/B01M8G9HYE",
      "完整详情": true
    },
    {
      "排名": 48,
      "ASIN编号": "B0F96F3XWF",
      "商品名称": "King Dog & Cat 狗狗训练垫，40片装，60x60厘米，6层超强吸收，洁净卫生",
      "品牌": "King Dog & Cat",
      "评分": 4.7,
      "评论数": 9,
      "价格(墨西哥比索)": 285.0,
      "月销量": 900,
      "销量依据": "亚马逊官方(上月购买量)",
      "上架时间": "",
      "在售月数": null,
      "变体数量": 1,
      "卖家": "Zeitex",
      "卖家类型": "第三方(墨西哥)",
      "卖家所在地": "墨西哥",
      "卖家详细地址": "墨西哥/52764/墨西哥州/韦尔基鲁坎德德戈利亚多/大街赫苏斯德尔蒙特39号2层2B室赫苏斯德尔蒙特",
      "配送方式": "FBA",
      "商品链接": "https://www.amazon.com.mx/dp/B0F96F3XWF",
      "完整详情": true
    },
    {
      "排名": 49,
      "ASIN编号": "B0FN2WXY5M",
      "商品名称": "270只薰衣草香味便携狗屎袋（带分配器与夹子），可生物降解，18卷装",
      "品牌": "ESRAIN",
      "评分": 4.8,
      "评论数": 88,
      "价格(墨西哥比索)": 157.5,
      "月销量": 300,
      "销量依据": "亚马逊官方(上月购买量)",
      "上架时间": "",
      "在售月数": null,
      "变体数量": 1,
      "卖家": "ESRAIN",
      "卖家类型": "品牌方(中国)",
      "卖家所在地": "中国",
      "卖家详细地址": "中国/518108/广东/宝安区/深圳市/金凯进厂区厂房一C403/石岩街道石龙社区",
      "配送方式": "FBA",
      "商品链接": "https://www.amazon.com.mx/dp/B0FN2WXY5M",
      "完整详情": true
    },
    {
      "排名": 50,
      "ASIN编号": "B0153V47YU",
      "商品名称": "Nupec小型犬幼犬狗粮，含维生素E和硒，2公斤装",
      "品牌": "Nupec",
      "评分": 4.8,
      "评论数": 3167,
      "价格(墨西哥比索)": 439.0,
      "月销量": 1000,
      "销量依据": "亚马逊官方(上月购买量)",
      "上架时间": "2015-10-06",
      "在售月数": 130,
      "变体数量": 1,
      "卖家": "Amikoo Peek",
      "卖家类型": "第三方(墨西哥)",
      "卖家所在地": "墨西哥",
      "卖家详细地址": "墨西哥/52927/墨西哥州/阿蒂萨潘德萨拉戈萨/马林切 50, 科洛尼亚圣米格尔霍奇曼加",
      "配送方式": "FBA",
      "商品链接": "https://www.amazon.com.mx/dp/B0153V47YU",
      "完整详情": true
    },
    {
      "排名": 51,
      "ASIN编号": "B0DL98VSFP",
      "商品名称": "540个薰衣草香味便携式宠物便便袋，含分配器和夹子，可降解，36卷",
      "品牌": "ESRAIN",
      "评分": 4.8,
      "评论数": 303,
      "价格(墨西哥比索)": 288.0,
      "月销量": 800,
      "销量依据": "亚马逊官方(上月购买量)",
      "上架时间": "",
      "在售月数": null,
      "变体数量": 1,
      "卖家": "ESRAIN",
      "卖家类型": "品牌方(中国)",
      "卖家所在地": "中国",
      "卖家详细地址": "中国/518108/广东/宝安区/深圳市/金凯进厂区厂房一C403/石岩街道石龙社区",
      "配送方式": "FBA",
      "商品链接": "https://www.amazon.com.mx/dp/B0DL98VSFP",
      "完整详情": true
    },
    {
      "排名": 52,
      "ASIN编号": "B08B1XMBV1",
      "商品名称": "Medical Solutions 可调节伊丽莎白圈 适用于猫狗 术后防护防止舔咬伤口 3号（29厘米）",
      "品牌": "Fancy Pets",
      "评分": 4.5,
      "评论数": 3048,
      "价格(墨西哥比索)": 114.12,
      "月销量": 100,
      "销量依据": "亚马逊官方(上月购买量)",
      "上架时间": "2020-06-11",
      "在售月数": 73,
      "变体数量": 11,
      "卖家": "Amazon México",
      "卖家类型": "亚马逊自营",
      "卖家所在地": "",
      "卖家详细地址": "",
      "配送方式": "亚马逊自营配送",
      "商品链接": "https://www.amazon.com.mx/dp/B08B1XMBV1",
      "完整详情": true
    },
    {
      "排名": 53,
      "ASIN编号": "B0CF64R8Y1",
      "商品名称": "Dogelthy 肠胃护理益生元益生菌 狗狗营养补充剂 每勺含超30亿CFU 狗粮或生骨肉伴侣 270g（鱼肉味）",
      "品牌": "Dogelthy",
      "评分": 4.6,
      "评论数": 1172,
      "价格(墨西哥比索)": 641.0,
      "月销量": 200,
      "销量依据": "亚马逊官方(上月购买量)",
      "上架时间": "2023-08-09",
      "在售月数": 36,
      "变体数量": 4,
      "卖家": "Dogelthy",
      "卖家类型": "品牌方(墨西哥)",
      "卖家所在地": "墨西哥",
      "卖家详细地址": "墨西哥/45019/哈利斯科州/萨波潘/圣胡安-德奥科坦/5月5日 #15 内6",
      "配送方式": "FBA",
      "商品链接": "https://www.amazon.com.mx/dp/B0CF64R8Y1",
      "完整详情": true
    },
    {
      "排名": 54,
      "ASIN编号": "B09KQVCC67",
      "商品名称": "Nature's Miracle 狗狗除尿渍加强型 946毫升",
      "品牌": "Nature's Miracle",
      "评分": 4.4,
      "评论数": 4256,
      "价格(墨西哥比索)": 239.25,
      "月销量": 800,
      "销量依据": "亚马逊官方(上月购买量)",
      "上架时间": "2021-11-01",
      "在售月数": 57,
      "变体数量": 3,
      "卖家": "Amazon México",
      "卖家类型": "亚马逊自营",
      "卖家所在地": "",
      "卖家详细地址": "",
      "配送方式": "亚马逊自营配送",
      "商品链接": "https://www.amazon.com.mx/dp/B09KQVCC67",
      "完整详情": true
    },
    {
      "排名": 55,
      "ASIN编号": "B0BKK5XWDL",
      "商品名称": "Raganet 宠物运输箱，适用猫狗，便携包，最大承重10公斤，尺寸：长42厘米×宽20厘米×高25厘米，旅行和车载背包，粉色",
      "品牌": "Raganet",
      "评分": 4.6,
      "评论数": 1249,
      "价格(墨西哥比索)": 279.0,
      "月销量": 300,
      "销量依据": "亚马逊官方(上月购买量)",
      "上架时间": "2022-10-26",
      "在售月数": 45,
      "变体数量": 3,
      "卖家": "Raga Basics",
      "卖家类型": "第三方(墨西哥)",
      "卖家所在地": "墨西哥",
      "卖家详细地址": "墨西哥/52790/墨西哥州/惠克斯基卢坎德德戈利亚多/多斯里奥斯/维森特格雷罗大道",
      "配送方式": "FBA",
      "商品链接": "https://www.amazon.com.mx/dp/B0BKK5XWDL",
      "完整详情": true
    },
    {
      "排名": 56,
      "ASIN编号": "B0GKFZ13XV",
      "商品名称": "安全门，婴儿门，76-125厘米，宠物门，儿童安全门，免打孔，适用于楼梯",
      "品牌": "MOXIMX",
      "评分": 4.7,
      "评论数": 248,
      "价格(墨西哥比索)": 1099.97,
      "月销量": 200,
      "销量依据": "亚马逊官方(上月购买量)",
      "上架时间": "",
      "在售月数": null,
      "变体数量": 2,
      "卖家": "duanyuUS",
      "卖家类型": "第三方(中国)",
      "卖家所在地": "中国",
      "卖家详细地址": "中国/422700/湖南省/新宁县/邵阳市/金石镇河边街37号",
      "配送方式": "FBA",
      "商品链接": "https://www.amazon.com.mx/dp/B0GKFZ13XV",
      "完整详情": true
    },
    {
      "排名": 57,
      "ASIN编号": "B00EJXIZ60",
      "商品名称": "Earth Rated - 狗狗粪便袋，120个装，8卷，无味",
      "品牌": "Earth Rated",
      "评分": 4.9,
      "评论数": 16953,
      "价格(墨西哥比索)": 134.25,
      "月销量": 1000,
      "销量依据": "亚马逊官方(上月购买量)",
      "上架时间": "2014-02-23",
      "在售月数": 149,
      "变体数量": 1,
      "卖家": "Amazon México",
      "卖家类型": "亚马逊自营",
      "卖家所在地": "",
      "卖家详细地址": "",
      "配送方式": "亚马逊自营配送",
      "商品链接": "https://www.amazon.com.mx/dp/B00EJXIZ60",
      "完整详情": true
    },
    {
      "排名": 58,
      "ASIN编号": "B07L9JHXJR",
      "商品名称": "荒野盛宴太平洋溪流顶级无谷物高蛋白狗粮，主料烟熏三文鱼，全犬期适用，含益生菌促进消化健康",
      "品牌": "Taste Of The Wild",
      "评分": 4.7,
      "评论数": 6609,
      "价格(墨西哥比索)": 1599.0,
      "月销量": 900,
      "销量依据": "亚马逊官方(上月购买量)",
      "上架时间": "2019-01-30",
      "在售月数": 90,
      "变体数量": 1,
      "卖家": "Amazon México",
      "卖家类型": "亚马逊自营",
      "卖家所在地": "",
      "卖家详细地址": "",
      "配送方式": "亚马逊自营配送",
      "商品链接": "https://www.amazon.com.mx/dp/B07L9JHXJR",
      "完整详情": true
    },
    {
      "排名": 59,
      "ASIN编号": "B08WLPDWV6",
      "商品名称": "Barkys狗零食含Omega 3和6，2.5公斤",
      "品牌": "Cowjag",
      "评分": 4.8,
      "评论数": 970,
      "价格(墨西哥比索)": 348.76,
      "月销量": 1000,
      "销量依据": "亚马逊官方(上月购买量)",
      "上架时间": "2021-02-15",
      "在售月数": 65,
      "变体数量": 1,
      "卖家": "Amazon México",
      "卖家类型": "亚马逊自营",
      "卖家所在地": "",
      "卖家详细地址": "",
      "配送方式": "亚马逊自营配送",
      "商品链接": "https://www.amazon.com.mx/dp/B08WLPDWV6",
      "完整详情": true
    },
    {
      "排名": 60,
      "ASIN编号": "B07WZ2KN1V",
      "商品名称": "Cloralex宠物消除异味10升",
      "品牌": "Cloralex",
      "评分": 4.8,
      "评论数": 937,
      "价格(墨西哥比索)": 256.0,
      "月销量": 900,
      "销量依据": "亚马逊官方(上月购买量)",
      "上架时间": "",
      "在售月数": null,
      "变体数量": 1,
      "卖家": "Amazon México",
      "卖家类型": "亚马逊自营",
      "卖家所在地": "",
      "卖家详细地址": "",
      "配送方式": "亚马逊自营配送",
      "商品链接": "https://www.amazon.com.mx/dp/B07WZ2KN1V",
      "完整详情": true
    },
    {
      "排名": 61,
      "ASIN编号": "B01FKNX4R2",
      "商品名称": "加纳多幼犬全犬种干粮 20kg",
      "品牌": "Ganador",
      "评分": 4.7,
      "评论数": 1150,
      "价格(墨西哥比索)": 718.0,
      "月销量": 900,
      "销量依据": "亚马逊官方(上月购买量)",
      "上架时间": "2016-11-24",
      "在售月数": 116,
      "变体数量": 1,
      "卖家": "Amazon México",
      "卖家类型": "亚马逊自营",
      "卖家所在地": "",
      "卖家详细地址": "",
      "配送方式": "亚马逊自营配送",
      "商品链接": "https://www.amazon.com.mx/dp/B01FKNX4R2",
      "完整详情": true
    },
    {
      "排名": 62,
      "ASIN编号": "B0CG33YCN1",
      "商品名称": "中小型及大型犬安全胸背带（含1.5米牵引绳）深蓝色 XL",
      "品牌": "UNA MASCOTA",
      "评分": 4.6,
      "评论数": 1288,
      "价格(墨西哥比索)": 219.0,
      "月销量": null,
      "销量依据": "",
      "上架时间": "2023-08-19",
      "在售月数": 35,
      "变体数量": 63,
      "卖家": "COMERSTAT",
      "卖家类型": "第三方(墨西哥)",
      "卖家所在地": "墨西哥",
      "卖家详细地址": "墨西哥/06000/墨西哥城/墨西哥城/中心（区域1）/中央轴线拉扎罗·卡德纳斯 119 LOC 2 3",
      "配送方式": "FBA",
      "商品链接": "https://www.amazon.com.mx/dp/B0CG33YCN1",
      "完整详情": true
    },
    {
      "排名": 63,
      "ASIN编号": "B0155E0168",
      "商品名称": "Fancy Pets 不锈钢狗碗，8盎司（227克）",
      "品牌": "Fancy Pets",
      "评分": 4.7,
      "评论数": 6651,
      "价格(墨西哥比索)": 40.5,
      "月销量": 700,
      "销量依据": "亚马逊官方(上月购买量)",
      "上架时间": "2016-01-22",
      "在售月数": 126,
      "变体数量": 7,
      "卖家": "Amazon México",
      "卖家类型": "亚马逊自营",
      "卖家所在地": "",
      "卖家详细地址": "",
      "配送方式": "亚马逊自营配送",
      "商品链接": "https://www.amazon.com.mx/dp/B0155E0168",
      "完整详情": true
    },
    {
      "排名": 64,
      "ASIN编号": "B074M2D1LJ",
      "商品名称": "完美感官优质成犬粮中大型犬用MLB15公斤 - 100%天然含Omega-3、益生菌、抗氧化剂 - 高消化率",
      "品牌": "Perfect Sense",
      "评分": 4.6,
      "评论数": 737,
      "价格(墨西哥比索)": 1549.0,
      "月销量": 500,
      "销量依据": "亚马逊官方(上月购买量)",
      "上架时间": "2017-08-06",
      "在售月数": 108,
      "变体数量": 3,
      "卖家": "Amazon México",
      "卖家类型": "亚马逊自营",
      "卖家所在地": "",
      "卖家详细地址": "",
      "配送方式": "亚马逊自营配送",
      "商品链接": "https://www.amazon.com.mx/dp/B074M2D1LJ",
      "完整详情": true
    },
    {
      "排名": 65,
      "ASIN编号": "B09232RF2N",
      "商品名称": "完美感知老年犬粮3公斤",
      "品牌": "Perfect Sense",
      "评分": 4.7,
      "评论数": 717,
      "价格(墨西哥比索)": 439.0,
      "月销量": 300,
      "销量依据": "亚马逊官方(上月购买量)",
      "上架时间": "2019-09-17",
      "在售月数": 82,
      "变体数量": 3,
      "卖家": "Amazon México",
      "卖家类型": "亚马逊自营",
      "卖家所在地": "",
      "卖家详细地址": "",
      "配送方式": "亚马逊自营配送",
      "商品链接": "https://www.amazon.com.mx/dp/B09232RF2N",
      "完整详情": true
    },
    {
      "排名": 66,
      "ASIN编号": "B0D7XPXCSL",
      "商品名称": "TP-Link Tapo 2K室内安全摄像头，带全景/倾斜功能，用于婴儿监控、宠物，移动侦测，双向音频，存储，黑色，C211，2件装",
      "品牌": "Tapo",
      "评分": 4.7,
      "评论数": 3137,
      "价格(墨西哥比索)": 803.09,
      "月销量": 500,
      "销量依据": "亚马逊官方(上月购买量)",
      "上架时间": "",
      "在售月数": null,
      "变体数量": 2,
      "卖家": "Amazon México",
      "卖家类型": "亚马逊自营",
      "卖家所在地": "",
      "卖家详细地址": "",
      "配送方式": "亚马逊自营配送",
      "商品链接": "https://www.amazon.com.mx/dp/B0D7XPXCSL",
      "完整详情": true
    },
    {
      "排名": 67,
      "ASIN编号": "B0088LIINY",
      "商品名称": "Earth Rated 狗狗粪便袋，120袋8卷，薰衣草香",
      "品牌": "Earth Rated",
      "评分": 4.9,
      "评论数": 200825,
      "价格(墨西哥比索)": 165.0,
      "月销量": 900,
      "销量依据": "亚马逊官方(上月购买量)",
      "上架时间": "",
      "在售月数": null,
      "变体数量": 4,
      "卖家": "Amazon México",
      "卖家类型": "亚马逊自营",
      "卖家所在地": "",
      "卖家详细地址": "",
      "配送方式": "亚马逊自营配送",
      "商品链接": "https://www.amazon.com.mx/dp/B0088LIINY",
      "完整详情": true
    },
    {
      "排名": 68,
      "ASIN编号": "B0CN7CRSLH",
      "商品名称": "Raganet 宠物座套，汽车座椅沙发保护罩，适合狗和猫，用于后座、后备箱或沙发，尺寸：137*147*40厘米，防水（全黑）",
      "品牌": "Raganet",
      "评分": 4.3,
      "评论数": 1676,
      "价格(墨西哥比索)": 269.0,
      "月销量": 600,
      "销量依据": "亚马逊官方(上月购买量)",
      "上架时间": "",
      "在售月数": null,
      "变体数量": 2,
      "卖家": "Raga Basics",
      "卖家类型": "第三方(墨西哥)",
      "卖家所在地": "墨西哥",
      "卖家详细地址": "墨西哥/52790/墨西哥/维克斯基卢坎德德戈利亚多/多斯里奥斯/比森特·格雷罗大道",
      "配送方式": "FBA",
      "商品链接": "https://www.amazon.com.mx/dp/B0CN7CRSLH",
      "完整详情": true
    },
    {
      "排名": 69,
      "ASIN编号": "B07NSD6XW3",
      "商品名称": "Nupec小型老年犬干粮，2公斤，1包装",
      "品牌": "Nupec",
      "评分": 4.9,
      "评论数": 2271,
      "价格(墨西哥比索)": 499.0,
      "月销量": 1000,
      "销量依据": "亚马逊官方(上月购买量)",
      "上架时间": "2019-03-18",
      "在售月数": 88,
      "变体数量": 1,
      "卖家": "Amikoo Peek",
      "卖家类型": "第三方(墨西哥)",
      "卖家所在地": "墨西哥",
      "卖家详细地址": "MX/52927/墨西哥州/阿蒂萨潘-德萨拉戈萨/马林切 50, 圣米格尔-霍奇曼加社区",
      "配送方式": "FBA",
      "商品链接": "https://www.amazon.com.mx/dp/B07NSD6XW3",
      "完整详情": true
    },
    {
      "排名": 70,
      "ASIN编号": "B0B84V22ZJ",
      "商品名称": "RENDIN 255只可生物降解狗袋，防漏带香味，17卷+1分配器+1夹子",
      "品牌": "RENDIN",
      "评分": 4.8,
      "评论数": 1756,
      "价格(墨西哥比索)": 199.0,
      "月销量": 600,
      "销量依据": "亚马逊官方(上月购买量)",
      "上架时间": "",
      "在售月数": null,
      "变体数量": 4,
      "卖家": "L-JL",
      "卖家类型": "第三方(中国)",
      "卖家所在地": "中国",
      "卖家详细地址": "中国/518129/广东/龙岗/深圳/21栋203室/坂田街道坂田社区第三工业区",
      "配送方式": "FBA",
      "商品链接": "https://www.amazon.com.mx/dp/B0B84V22ZJ",
      "完整详情": true
    },
    {
      "排名": 71,
      "ASIN编号": "B018TYLZU2",
      "商品名称": "Fancy Pets 狗狗训练垫 Doggie Grass GDE | 带托盘格栅的合成草皮 | 气味控制且易清洁",
      "品牌": "Fancy Pets",
      "评分": 4.4,
      "评论数": 10072,
      "价格(墨西哥比索)": 529.0,
      "月销量": 600,
      "销量依据": "亚马逊官方(上月购买量)",
      "上架时间": "2015-12-02",
      "在售月数": 128,
      "变体数量": 3,
      "卖家": "Amazon México",
      "卖家类型": "亚马逊自营",
      "卖家所在地": "",
      "卖家详细地址": "",
      "配送方式": "亚马逊自营配送",
      "商品链接": "https://www.amazon.com.mx/dp/B018TYLZU2",
      "完整详情": true
    },
    {
      "排名": 72,
      "ASIN编号": "B07PSK15Y2",
      "商品名称": "Nupec 老年小型犬干粮 - 1 x 8 千克",
      "品牌": "Nupec",
      "评分": 4.8,
      "评论数": 4257,
      "价格(墨西哥比索)": 1548.0,
      "月销量": 1000,
      "销量依据": "亚马逊官方(上月购买量)",
      "上架时间": "2019-03-18",
      "在售月数": 88,
      "变体数量": 1,
      "卖家": "Ros Pet-Shop",
      "卖家类型": "第三方(墨西哥)",
      "卖家所在地": "墨西哥",
      "卖家详细地址": "墨西哥/72220/普埃布拉/英雄普埃布拉德萨拉戈萨/马拉维利亚斯/C街24号普埃布拉2000工业园",
      "配送方式": "FBA",
      "商品链接": "https://www.amazon.com.mx/dp/B07PSK15Y2",
      "完整详情": true
    },
    {
      "排名": 73,
      "ASIN编号": "B07X148WCW",
      "商品名称": "Purina One 中大型犬成年犬粮 鸡肉牛肉味 7公斤",
      "品牌": "WeTap",
      "评分": 4.6,
      "评论数": 733,
      "价格(墨西哥比索)": 499.33,
      "月销量": 700,
      "销量依据": "亚马逊官方(上月购买量)",
      "上架时间": "2019-08-29",
      "在售月数": 83,
      "变体数量": 1,
      "卖家": "Amazon México",
      "卖家类型": "亚马逊自营",
      "卖家所在地": "",
      "卖家详细地址": "",
      "配送方式": "亚马逊自营配送",
      "商品链接": "https://www.amazon.com.mx/dp/B07X148WCW",
      "完整详情": true
    },
    {
      "排名": 74,
      "ASIN编号": "B0H46Y7Q4H",
      "商品名称": "LUDOS 湿巾，日常用犬猫湿巾，含芦荟和维生素E，每包80片（两包装）",
      "品牌": "LUDOS",
      "评分": 4.7,
      "评论数": 501,
      "价格(墨西哥比索)": 86.0,
      "月销量": null,
      "销量依据": "",
      "上架时间": "2023-12-06",
      "在售月数": 32,
      "变体数量": 2,
      "卖家": "Amazon México",
      "卖家类型": "亚马逊自营",
      "卖家所在地": "",
      "卖家详细地址": "",
      "配送方式": "亚马逊自营配送",
      "商品链接": "https://www.amazon.com.mx/dp/B0H46Y7Q4H",
      "完整详情": true
    },
    {
      "排名": 75,
      "ASIN编号": "B0CSTG692R",
      "商品名称": "Fancy Pets 大型狗狗降温垫 Aqua Cool - 自动冷却、便携、无毒，室内外通用",
      "品牌": "Fancy Pets",
      "评分": 4.3,
      "评论数": 956,
      "价格(墨西哥比索)": 399.0,
      "月销量": 200,
      "销量依据": "亚马逊官方(上月购买量)",
      "上架时间": "2024-01-19",
      "在售月数": 30,
      "变体数量": 5,
      "卖家": "Amazon México",
      "卖家类型": "亚马逊自营",
      "卖家所在地": "",
      "卖家详细地址": "",
      "配送方式": "亚马逊自营配送",
      "商品链接": "https://www.amazon.com.mx/dp/B0CSTG692R",
      "完整详情": true
    },
    {
      "排名": 76,
      "ASIN编号": "B0GQ68VD9R",
      "商品名称": "Fancy Pets 狗狗渐进式口腔护理套装，含可食用牙膏90g和指套，双头牙刷，犬用口腔卫生4件套",
      "品牌": "Fancy Pets",
      "评分": 4.7,
      "评论数": 53,
      "价格(墨西哥比索)": 119.0,
      "月销量": 1000,
      "销量依据": "亚马逊官方(上月购买量)",
      "上架时间": "2026-02-25",
      "在售月数": 5,
      "变体数量": 1,
      "卖家": "Amazon México",
      "卖家类型": "亚马逊自营",
      "卖家所在地": "",
      "卖家详细地址": "",
      "配送方式": "亚马逊自营配送",
      "商品链接": "https://www.amazon.com.mx/dp/B0GQ68VD9R",
      "完整详情": true
    },
    {
      "排名": 77,
      "ASIN编号": "B0B45BW58F",
      "商品名称": "Raganet 宠物运输背包，适用于猫狗，小型宠物便携背包（最大7公斤），尺寸：宽23cm 长33cm 高42cm，黑色",
      "品牌": "Raganet",
      "评分": 4.6,
      "评论数": 3075,
      "价格(墨西哥比索)": 298.0,
      "月销量": 700,
      "销量依据": "亚马逊官方(上月购买量)",
      "上架时间": "2022-06-15",
      "在售月数": 49,
      "变体数量": 3,
      "卖家": "Raga Basics",
      "卖家类型": "第三方(墨西哥)",
      "卖家所在地": "墨西哥",
      "卖家详细地址": "墨西哥/52790/墨西哥/维克斯基卢坎德戈利亚多/多斯里奥斯/比森特·格雷罗大道",
      "配送方式": "FBA",
      "商品链接": "https://www.amazon.com.mx/dp/B0B45BW58F",
      "完整详情": true
    },
    {
      "排名": 78,
      "ASIN编号": "B0929DKD6Z",
      "商品名称": "宝路成年犬热带能量牛肉火鸡10kg",
      "品牌": "Beneful",
      "评分": 4.8,
      "评论数": 1519,
      "价格(墨西哥比索)": 553.0,
      "月销量": 300,
      "销量依据": "亚马逊官方(上月购买量)",
      "上架时间": "2021-04-12",
      "在售月数": 63,
      "变体数量": 1,
      "卖家": "Amazon México",
      "卖家类型": "亚马逊自营",
      "卖家所在地": "",
      "卖家详细地址": "",
      "配送方式": "亚马逊自营配送",
      "商品链接": "https://www.amazon.com.mx/dp/B0929DKD6Z",
      "完整详情": true
    },
    {
      "排名": 79,
      "ASIN编号": "B07ZV7G6Y6",
      "商品名称": "Purina Beneful 成年犬迷你小型犬牛肉米饭口味 100g×20包",
      "品牌": "WeTap",
      "评分": 4.7,
      "评论数": 1498,
      "价格(墨西哥比索)": 270.18,
      "月销量": 600,
      "销量依据": "亚马逊官方(上月购买量)",
      "上架时间": "2019-10-31",
      "在售月数": 81,
      "变体数量": 1,
      "卖家": "Amazon México",
      "卖家类型": "亚马逊自营",
      "卖家所在地": "",
      "卖家详细地址": "",
      "配送方式": "亚马逊自营配送",
      "商品链接": "https://www.amazon.com.mx/dp/B07ZV7G6Y6",
      "完整详情": true
    },
    {
      "排名": 80,
      "ASIN编号": "B096N1C82L",
      "商品名称": "Purina One 成年迷你及小型犬粮 鸡肉牛肉味 3.5kg",
      "品牌": "Purina One Dry Perro",
      "评分": 4.6,
      "评论数": 253,
      "价格(墨西哥比索)": 257.3,
      "月销量": 500,
      "销量依据": "亚马逊官方(上月购买量)",
      "上架时间": "2021-06-04",
      "在售月数": 62,
      "变体数量": 1,
      "卖家": "Amazon México",
      "卖家类型": "亚马逊自营",
      "卖家所在地": "",
      "卖家详细地址": "",
      "配送方式": "亚马逊自营配送",
      "商品链接": "https://www.amazon.com.mx/dp/B096N1C82L",
      "完整详情": true
    },
    {
      "排名": 81,
      "ASIN编号": "B0G2CGCRN5",
      "商品名称": "Dogelthy过敏综合配方 天然抗过敏犬用补充剂 无瘙痒不适 支持免疫系统、皮肤和消化健康 猪肉味 270克",
      "品牌": "Dogelthy",
      "评分": 4.2,
      "评论数": 112,
      "价格(墨西哥比索)": 755.0,
      "月销量": 400,
      "销量依据": "亚马逊官方(上月购买量)",
      "上架时间": "2025-11-14",
      "在售月数": 8,
      "变体数量": 2,
      "卖家": "Dogelthy",
      "卖家类型": "品牌方(墨西哥)",
      "卖家所在地": "墨西哥",
      "卖家详细地址": "墨西哥/45019/哈利斯科/萨波潘/圣胡安德奥科坦/五月五日 #15 内6",
      "配送方式": "FBA",
      "商品链接": "https://www.amazon.com.mx/dp/B0G2CGCRN5",
      "完整详情": true
    },
    {
      "排名": 82,
      "ASIN编号": "B0DTHXGCTH",
      "商品名称": "HomeChi 狗狗恢复服 母狗手术衫 | 专业绝育腹部伤口防舔咬 XL 深蓝色",
      "品牌": "HomeChi",
      "评分": 4.5,
      "评论数": 451,
      "价格(墨西哥比索)": 339.99,
      "月销量": null,
      "销量依据": "",
      "上架时间": "2025-01-20",
      "在售月数": 18,
      "变体数量": 75,
      "卖家": "ZJFF MX LLC",
      "卖家类型": "第三方(中国)",
      "卖家所在地": "中国",
      "卖家详细地址": "中国/518129/广东省/龙岗区/深圳市/F栋六层609/坂田街道大发埔社区布龙路663号",
      "配送方式": "FBA",
      "商品链接": "https://www.amazon.com.mx/dp/B0DTHXGCTH",
      "完整详情": true
    },
    {
      "排名": 83,
      "ASIN编号": "B01FVRFC7W",
      "商品名称": "Barkys培根波浪小培根狗零食，567克",
      "品牌": "BARKYS",
      "评分": 4.8,
      "评论数": 760,
      "价格(墨西哥比索)": 191.0,
      "月销量": 700,
      "销量依据": "亚马逊官方(上月购买量)",
      "上架时间": "2016-05-19",
      "在售月数": 122,
      "变体数量": 1,
      "卖家": "Amazon México",
      "卖家类型": "亚马逊自营",
      "卖家所在地": "",
      "卖家详细地址": "",
      "配送方式": "亚马逊自营配送",
      "商品链接": "https://www.amazon.com.mx/dp/B01FVRFC7W",
      "完整详情": true
    },
    {
      "排名": 84,
      "ASIN编号": "B01A1DJ4GG",
      "商品名称": "Purina Beneful成犬小型犬粮牛肉味4kg",
      "品牌": "Purina",
      "评分": 4.8,
      "评论数": 1479,
      "价格(墨西哥比索)": 284.0,
      "月销量": 700,
      "销量依据": "亚马逊官方(上月购买量)",
      "上架时间": "2015-12-31",
      "在售月数": 127,
      "变体数量": 1,
      "卖家": "Amazon México",
      "卖家类型": "亚马逊自营",
      "卖家所在地": "",
      "卖家详细地址": "",
      "配送方式": "亚马逊自营配送",
      "商品链接": "https://www.amazon.com.mx/dp/B01A1DJ4GG",
      "完整详情": true
    },
    {
      "排名": 85,
      "ASIN编号": "B0F5YND3J6",
      "商品名称": "MAGMALIFE 狗狗训练垫60x60cm，50片超强吸水防漏宠物一次性垫，活性炭除臭速干训练尿片",
      "品牌": "MAGMALIFE",
      "评分": 4.4,
      "评论数": 8,
      "价格(墨西哥比索)": 245.0,
      "月销量": 50,
      "销量依据": "亚马逊官方(上月购买量)",
      "上架时间": "",
      "在售月数": null,
      "变体数量": 2,
      "卖家": "Zavix Brands",
      "卖家类型": "第三方(墨西哥)",
      "卖家所在地": "墨西哥",
      "卖家详细地址": "墨西哥/11500/米格尔·伊达尔戈/墨西哥城/内504/普雷萨萨利尼利亚斯 370",
      "配送方式": "FBA",
      "商品链接": "https://www.amazon.com.mx/dp/B0F5YND3J6",
      "完整详情": true
    },
    {
      "排名": 86,
      "ASIN编号": "B0BPN22XQT",
      "商品名称": "Platina Plus - 宠物除臭剂 - 超浓缩 - 可洗100次 - 去渍 - 适用于户外、室内、布料和家具（500毫升）",
      "品牌": "PLATINA",
      "评分": 4.4,
      "评论数": 846,
      "价格(墨西哥比索)": 290.0,
      "月销量": 800,
      "销量依据": "亚马逊官方(上月购买量)",
      "上架时间": "",
      "在售月数": null,
      "变体数量": 1,
      "卖家": "USA Detergente",
      "卖家类型": "第三方(墨西哥)",
      "卖家所在地": "墨西哥",
      "卖家详细地址": "墨西哥/66420/新莱昂/圣尼古拉斯德洛斯加尔萨/铺位/巴拉甘大道205号大学别墅社区",
      "配送方式": "FBA",
      "商品链接": "https://www.amazon.com.mx/dp/B0BPN22XQT",
      "完整详情": true
    },
    {
      "排名": 87,
      "ASIN编号": "B00NLMJ6F4",
      "商品名称": "VIRBAC Nutri-Plus营养补充凝胶120克，兽医专用犬猫用，补充能量与维生素，快速恢复，适口性佳",
      "品牌": "Virbac",
      "评分": 4.8,
      "评论数": 320,
      "价格(墨西哥比索)": 334.0,
      "月销量": 700,
      "销量依据": "亚马逊官方(上月购买量)",
      "上架时间": "2015-09-08",
      "在售月数": 131,
      "变体数量": 1,
      "卖家": "Virbac",
      "卖家类型": "品牌方(墨西哥)",
      "卖家所在地": "墨西哥",
      "卖家详细地址": "墨西哥/45010/哈利斯科/萨波潘/瓜达拉哈拉科技园/英国大道5070",
      "配送方式": "FBA",
      "商品链接": "https://www.amazon.com.mx/dp/B00NLMJ6F4",
      "完整详情": true
    },
    {
      "排名": 88,
      "ASIN编号": "B01MTK91PJ",
      "商品名称": "宠爱狗狗洗发水500毫升 | 印楝油、肉桂和葡萄柚，pH平衡，深层清洁，无浓烈香味，兽医使用，所有犬种",
      "品牌": "Perro Consentido",
      "评分": 4.7,
      "评论数": 1242,
      "价格(墨西哥比索)": 89.0,
      "月销量": 700,
      "销量依据": "亚马逊官方(上月购买量)",
      "上架时间": "",
      "在售月数": null,
      "变体数量": 1,
      "卖家": "Amazon México",
      "卖家类型": "亚马逊自营",
      "卖家所在地": "",
      "卖家详细地址": "",
      "配送方式": "亚马逊自营配送",
      "商品链接": "https://www.amazon.com.mx/dp/B01MTK91PJ",
      "完整详情": true
    },
    {
      "排名": 89,
      "ASIN编号": "B07BDVS94Q",
      "商品名称": "Perfect Sense 成年犬 SB 3公斤",
      "品牌": "Perfect Sense",
      "评分": 4.7,
      "评论数": 850,
      "价格(墨西哥比索)": 389.0,
      "月销量": 200,
      "销量依据": "亚马逊官方(上月购买量)",
      "上架时间": "2018-03-12",
      "在售月数": 101,
      "变体数量": 3,
      "卖家": "Amazon México",
      "卖家类型": "亚马逊自营",
      "卖家所在地": "",
      "卖家详细地址": "",
      "配送方式": "亚马逊自营配送",
      "商品链接": "https://www.amazon.com.mx/dp/B07BDVS94Q",
      "完整详情": true
    },
    {
      "排名": 90,
      "ASIN编号": "B0BRJV1W44",
      "商品名称": "4L酶解尿液清洁剂 | 去除宠物污渍异味 | 家用表面安全 | 无氯无毒的深层清洁 | 先进配方",
      "品牌": "Alamazonas",
      "评分": 4.2,
      "评论数": 106,
      "价格(墨西哥比索)": 549.0,
      "月销量": 500,
      "销量依据": "亚马逊官方(上月购买量)",
      "上架时间": "",
      "在售月数": null,
      "变体数量": 4,
      "卖家": "MERCHTONCOM",
      "卖家类型": "第三方(墨西哥)",
      "卖家所在地": "墨西哥",
      "卖家详细地址": "墨西哥/45615/哈利斯科/特拉凯帕克/65/赫苏斯拉米雷斯",
      "配送方式": "FBA",
      "商品链接": "https://www.amazon.com.mx/dp/B0BRJV1W44",
      "完整详情": true
    },
    {
      "排名": 91,
      "ASIN编号": "B009IXOFOC",
      "商品名称": "希尔思科学饮食成年犬羊肉味狗粮15公斤",
      "品牌": "Hill's Science Diet",
      "评分": 4.7,
      "评论数": 8832,
      "价格(墨西哥比索)": 2212.5,
      "月销量": 200,
      "销量依据": "亚马逊官方(上月购买量)",
      "上架时间": "2013-07-08",
      "在售月数": 157,
      "变体数量": 5,
      "卖家": "Amazon México",
      "卖家类型": "亚马逊自营",
      "卖家所在地": "",
      "卖家详细地址": "",
      "配送方式": "亚马逊自营配送",
      "商品链接": "https://www.amazon.com.mx/dp/B009IXOFOC",
      "完整详情": true
    },
    {
      "排名": 92,
      "ASIN编号": "B01M7NN6KX",
      "商品名称": "Nupec PENU7135 - AAAAAA狗狗口腔护理奖励零食，180克（包装可能不同）",
      "品牌": "Nupec",
      "评分": 4.8,
      "评论数": 2971,
      "价格(墨西哥比索)": 108.0,
      "月销量": 800,
      "销量依据": "亚马逊官方(上月购买量)",
      "上架时间": "2016-11-02",
      "在售月数": 117,
      "变体数量": 1,
      "卖家": "Amazon México",
      "卖家类型": "亚马逊自营",
      "卖家所在地": "",
      "卖家详细地址": "",
      "配送方式": "亚马逊自营配送",
      "商品链接": "https://www.amazon.com.mx/dp/B01M7NN6KX",
      "完整详情": true
    },
    {
      "排名": 93,
      "ASIN编号": "B0BQX4HLCS",
      "商品名称": "Raganet 便携宠物围栏，适用于中小型宠物，尺寸高58厘米、长78厘米，牛津布防水，室内外通用，安全耐用（灰色）",
      "品牌": "Raganet",
      "评分": 4.6,
      "评论数": 1060,
      "价格(墨西哥比索)": 279.0,
      "月销量": 800,
      "销量依据": "亚马逊官方(上月购买量)",
      "上架时间": "2022-12-23",
      "在售月数": 43,
      "变体数量": 2,
      "卖家": "Raga Basics",
      "卖家类型": "第三方(墨西哥)",
      "卖家所在地": "墨西哥",
      "卖家详细地址": "墨西哥/52790/墨西哥州/惠克斯基卢坎德戈利亚多/多斯里奥斯/维森特·格雷罗大道",
      "配送方式": "FBA",
      "商品链接": "https://www.amazon.com.mx/dp/B0BQX4HLCS",
      "完整详情": true
    },
    {
      "排名": 94,
      "ASIN编号": "B08QJNMHLZ",
      "商品名称": "Arm & Hammer 完整护理狗狗口腔套装 | 2.5盎司鸡肉味酶解牙膏、牙刷和指套刷 | 添加小苏打配方，清新口气，控制牙垢",
      "品牌": "Arm & Hammer",
      "评分": 4.6,
      "评论数": 3181,
      "价格(墨西哥比索)": 125.0,
      "月销量": 500,
      "销量依据": "亚马逊官方(上月购买量)",
      "上架时间": "",
      "在售月数": null,
      "变体数量": 1,
      "卖家": "Amazon México",
      "卖家类型": "亚马逊自营",
      "卖家所在地": "",
      "卖家详细地址": "",
      "配送方式": "亚马逊自营配送",
      "商品链接": "https://www.amazon.com.mx/dp/B08QJNMHLZ",
      "完整详情": true
    },
    {
      "排名": 95,
      "ASIN编号": "B0FJLF3L5M",
      "商品名称": "OSLIFE 狗碗，可调节5种高度的倾斜式狗食盆 | 慢食狗猫碗，含2个不锈钢碗，适合中小型及大型宠物",
      "品牌": "OSLIFE Sososy SUNSMELL",
      "评分": 4.8,
      "评论数": 101,
      "价格(墨西哥比索)": 396.7,
      "月销量": 400,
      "销量依据": "亚马逊官方(上月购买量)",
      "上架时间": "2025-07-23",
      "在售月数": 12,
      "变体数量": 1,
      "卖家": "HHHUIDA",
      "卖家类型": "第三方(中国)",
      "卖家所在地": "中国",
      "卖家详细地址": "中国/518129/广东省/深圳市/龙景科技园F栋601-6/龙岗区坂田街道马安堂社区布龙路335号",
      "配送方式": "FBA",
      "商品链接": "https://www.amazon.com.mx/dp/B0FJLF3L5M",
      "完整详情": true
    },
    {
      "排名": 96,
      "ASIN编号": "B09Y1RNQXL",
      "商品名称": "宝路小型犬鸡肉味软包，含天然成分、蛋白质和纤维，24包，每包100克",
      "品牌": "Pedigree",
      "评分": 4.8,
      "评论数": 636,
      "价格(墨西哥比索)": 225.25,
      "月销量": 800,
      "销量依据": "亚马逊官方(上月购买量)",
      "上架时间": "2022-04-15",
      "在售月数": 51,
      "变体数量": 1,
      "卖家": "Amazon México",
      "卖家类型": "亚马逊自营",
      "卖家所在地": "",
      "卖家详细地址": "",
      "配送方式": "亚马逊自营配送",
      "商品链接": "https://www.amazon.com.mx/dp/B09Y1RNQXL",
      "完整详情": true
    },
    {
      "排名": 97,
      "ASIN编号": "B08JRVB4BH",
      "商品名称": "Minino Plus 食谱湿粮，金枪鱼肉味，85克，灰色，24包装",
      "品牌": "LQNQ",
      "评分": 4.8,
      "评论数": 560,
      "价格(墨西哥比索)": 276.0,
      "月销量": 600,
      "销量依据": "亚马逊官方(上月购买量)",
      "上架时间": "2020-09-22",
      "在售月数": 70,
      "变体数量": 1,
      "卖家": "Amazon México",
      "卖家类型": "亚马逊自营",
      "卖家所在地": "",
      "卖家详细地址": "",
      "配送方式": "亚马逊自营配送",
      "商品链接": "https://www.amazon.com.mx/dp/B08JRVB4BH",
      "完整详情": true
    },
    {
      "排名": 98,
      "ASIN编号": "B0153V48QC",
      "商品名称": "Nupec狗粮，幼犬小型犬，含维生素E和硒，8公斤装。",
      "品牌": "Nupec",
      "评分": 4.8,
      "评论数": 4695,
      "价格(墨西哥比索)": 1372.0,
      "月销量": 600,
      "销量依据": "亚马逊官方(上月购买量)",
      "上架时间": "2015-11-13",
      "在售月数": 128,
      "变体数量": 1,
      "卖家": "Biencomelon",
      "卖家类型": "第三方(墨西哥)",
      "卖家所在地": "墨西哥",
      "卖家详细地址": "墨西哥/72130/普埃布拉/埃罗伊卡普埃布拉德萨拉戈萨/拉利伯塔德/10波尼恩特913B",
      "配送方式": "FBA",
      "商品链接": "https://www.amazon.com.mx/dp/B0153V48QC",
      "完整详情": true
    },
    {
      "排名": 99,
      "ASIN编号": "B0C6BW1K8R",
      "商品名称": "Raganet 宠物运输笼，金属门，可装5公斤以下小型宠物（长50x宽30x高30厘米）黑色",
      "品牌": "Raganet",
      "评分": 4.5,
      "评论数": 1180,
      "价格(墨西哥比索)": 379.0,
      "月销量": 300,
      "销量依据": "亚马逊官方(上月购买量)",
      "上架时间": "2023-05-25",
      "在售月数": 38,
      "变体数量": 4,
      "卖家": "Raga Basics",
      "卖家类型": "第三方(墨西哥)",
      "卖家所在地": "墨西哥",
      "卖家详细地址": "墨西哥/52790/墨西哥/维克斯基卢坎德戈亚多/多斯里奥斯/维森特格雷罗大道",
      "配送方式": "FBA",
      "商品链接": "https://www.amazon.com.mx/dp/B0C6BW1K8R",
      "完整详情": true
    },
    {
      "排名": 100,
      "ASIN编号": "B003CLAJ1E",
      "商品名称": "希尔思科学饮食小型迷你成犬7岁以上老年犬粮，鸡肉糙米味，2公斤",
      "品牌": "Hill's Science Diet",
      "评分": 4.8,
      "评论数": 3271,
      "价格(墨西哥比索)": 528.75,
      "月销量": 700,
      "销量依据": "亚马逊官方(上月购买量)",
      "上架时间": "2017-12-05",
      "在售月数": 104,
      "变体数量": 1,
      "卖家": "Amazon México",
      "卖家类型": "亚马逊自营",
      "卖家所在地": "",
      "卖家详细地址": "",
      "配送方式": "亚马逊自营配送",
      "商品链接": "https://www.amazon.com.mx/dp/B003CLAJ1E",
      "完整详情": true
    }
  ]
}